python_sdk_sync_test/__init__.py
python_sdk_sync_test/api.py
python_sdk_sync_test/client.py
python_sdk_sync_test/exceptions.py
python_sdk_sync_test/live_streams.py
python_sdk_sync_test/media.py
python_sdk_sync_test/playback_ids.py
python_sdk_sync_test/signing_keys.py
python_sdk_sync_test-0.1.0.dist-info/METADATA
python_sdk_sync_test-0.1.0.dist-info/WHEEL
python_sdk_sync_test-0.1.0.dist-info/top_level.txt
python_sdk_sync_test-0.1.0.dist-info/RECORD
